msal_requests_auth/__init__.py
msal_requests_auth/_version.py
msal_requests_auth/cache.py
msal_requests_auth/exceptions.py
msal_requests_auth/py.typed
msal_requests_auth/auth/__init__.py
msal_requests_auth/auth/base_auth_client.py
msal_requests_auth/auth/client_credential.py
msal_requests_auth/auth/device_code.py
msal_requests_auth-0.9.1.dist-info/licenses/LICENSE
msal_requests_auth-0.9.1.dist-info/METADATA
msal_requests_auth-0.9.1.dist-info/WHEEL
msal_requests_auth-0.9.1.dist-info/top_level.txt
msal_requests_auth-0.9.1.dist-info/RECORD
