Metadata-Version: 2.4
Name: msal_requests_auth
Version: 0.9.1
Summary: Authentication using python requests and MSAL
Home-page: https://github.com/corteva/msal-requests-auth
Download-URL: http://python.org/pypi/msal-requests-auth
Author: msal_requests_auth Contributors
Author-email: alansnow21@gmail.com
License: BSD License
Keywords: msal,requests
Platform: any
Classifier: Development Status :: 2 - Pre-Alpha
Classifier: Intended Audience :: Developers
Classifier: Natural Language :: English
Classifier: License :: OSI Approved :: BSD License
Classifier: Operating System :: OS Independent
Classifier: Programming Language :: Python
Classifier: Programming Language :: Python :: 3.10
Classifier: Programming Language :: Python :: 3.11
Classifier: Programming Language :: Python :: 3.12
Classifier: Programming Language :: Python :: 3
Classifier: Topic :: Software Development :: Libraries :: Python Modules
Classifier: Typing :: Typed
Requires-Python: >=3.10
License-File: LICENSE
Requires-Dist: platformdirs
Requires-Dist: msal
Requires-Dist: pyperclip
Requires-Dist: requests
Provides-Extra: keyring
Requires-Dist: keyring; extra == "keyring"
Provides-Extra: dev
Requires-Dist: pytest; extra == "dev"
Requires-Dist: pytest-cov; extra == "dev"
Requires-Dist: pre-commit; extra == "dev"
Requires-Dist: pylint; extra == "dev"
Provides-Extra: all
Requires-Dist: keyring; extra == "all"
Requires-Dist: pytest; extra == "all"
Requires-Dist: pytest-cov; extra == "all"
Requires-Dist: pre-commit; extra == "all"
Requires-Dist: pylint; extra == "all"
Dynamic: download-url
Dynamic: license-file
